aws_log_parser/__init__.py
aws_log_parser/aws/__init__.py
aws_log_parser/aws/client.py
aws_log_parser/aws/plugin.py
aws_log_parser/aws/s3.py
aws_log_parser/cli/__init__.py
aws_log_parser/cli/main.py
aws_log_parser/exceptions.py
aws_log_parser/interface.py
aws_log_parser/io.py
aws_log_parser/models.py
aws_log_parser/parser.py
aws_log_parser/util.py
aws_log_parser-3.0.2.dist-info/LICENSE
aws_log_parser-3.0.2.dist-info/METADATA
aws_log_parser-3.0.2.dist-info/WHEEL
aws_log_parser-3.0.2.dist-info/RECORD
