Metadata-Version: 2.1
Name: aws-log-parser
Version: 3.0.2
Summary: Parse AWS CloudFront and LoadBalancer logs into Python dataclasses.
License: Apache
Author: Derrick Petzold
Author-email: github@petzold.io
Requires-Python: >=3.10,<3.14
Classifier: License :: Other/Proprietary License
Classifier: Programming Language :: Python :: 3
Classifier: Programming Language :: Python :: 3.10
Classifier: Programming Language :: Python :: 3.11
Requires-Dist: boto3 (>=1.35.88,<2.0.0)
Requires-Dist: dataclasses-json (>=0.6.7,<0.7.0)
